tlb32/__init__.py
tlb32/tlb32.py
tlb32-0.1.1.dist-info/METADATA
tlb32-0.1.1.dist-info/WHEEL
tlb32-0.1.1.dist-info/entry_points.txt
tlb32-0.1.1.dist-info/RECORD
