Metadata-Version: 2.1
Name: tlb32
Version: 0.1.1
Summary: Tool for automatic calculation of operation codes in TL-B schemes.
Author: Continuation Team
Requires-Python: >=3.8,<4.0
Classifier: Programming Language :: Python :: 3
Classifier: Programming Language :: Python :: 3.8
Classifier: Programming Language :: Python :: 3.9
Classifier: Programming Language :: Python :: 3.10
Classifier: Programming Language :: Python :: 3.11
Classifier: Programming Language :: Python :: 3.12
Requires-Dist: Pygments (>=2.17.2,<3.0.0)
